odoo/addons/stock_barcodes_gs1_expiry/README.rst
odoo/addons/stock_barcodes_gs1_expiry/__init__.py
odoo/addons/stock_barcodes_gs1_expiry/__manifest__.py
odoo/addons/stock_barcodes_gs1_expiry/i18n/stock_barcodes_gs1_expiry.pot
odoo/addons/stock_barcodes_gs1_expiry/readme/CONTRIBUTORS.rst
odoo/addons/stock_barcodes_gs1_expiry/readme/DESCRIPTION.rst
odoo/addons/stock_barcodes_gs1_expiry/readme/USAGE.rst
odoo/addons/stock_barcodes_gs1_expiry/static/description/icon.png
odoo/addons/stock_barcodes_gs1_expiry/static/description/index.html
odoo/addons/stock_barcodes_gs1_expiry/tests/__init__.py
odoo/addons/stock_barcodes_gs1_expiry/tests/test_stock_barcodes_gs1_expiry.py
odoo/addons/stock_barcodes_gs1_expiry/tests/test_stock_barcodes_new_lot_gs1_expiry.py
odoo/addons/stock_barcodes_gs1_expiry/wizard/__init__.py
odoo/addons/stock_barcodes_gs1_expiry/wizard/stock_barcodes_read.py
odoo/addons/stock_barcodes_gs1_expiry/wizard/stock_production_lot.py
odoo/addons/stock_barcodes_gs1_expiry/wizard/stock_production_lot_views.xml
odoo11_addon_stock_barcodes_gs1_expiry-11.0.1.0.0.99.dev4.dist-info/METADATA
odoo11_addon_stock_barcodes_gs1_expiry-11.0.1.0.0.99.dev4.dist-info/WHEEL
odoo11_addon_stock_barcodes_gs1_expiry-11.0.1.0.0.99.dev4.dist-info/top_level.txt
odoo11_addon_stock_barcodes_gs1_expiry-11.0.1.0.0.99.dev4.dist-info/RECORD
